{
  "meta": {
    "concept": "Bubble Sort",
    "topic": "Sorting Algorithms",
    "educational_goal": "To demonstrate the Bubble Sort algorithm through interactive input and output.",
    "expected_interactions": [
      "User inputs number of elements",
      "User clicks sort button"
    ]
  },
  "states": [
    {
      "id": "S0_Idle",
      "label": "Idle",
      "type": "initial",
      "entry_actions": [
        "renderPage()"
      ],
      "exit_actions": [],
      "evidence": [
        "<input type=\"number\" id=\"n\" name=\"n\">",
        "<button id=\"sort-btn\">Sort</button>"
      ],
      "confidence": 1
    },
    {
      "id": "S1_Sorting",
      "label": "Sorting",
      "type": "processing",
      "entry_actions": [
        "bubbleSort(arr)"
      ],
      "exit_actions": [],
      "evidence": [
        "let n = parseInt(document.getElementById('n').value);",
        "let arr = Array.from({length: n}, () => Math.floor(Math.random() * 100));"
      ],
      "confidence": 1
    },
    {
      "id": "S2_Sorted",
      "label": "Sorted",
      "type": "final",
      "entry_actions": [
        "document.getElementById('result').innerHTML = 'Sorted array: ' + sortedArr.join(', ');"
      ],
      "exit_actions": [],
      "evidence": [
        "document.getElementById('result').innerHTML = 'Sorted array: ' + sortedArr.join(', ');"
      ],
      "confidence": 1
    }
  ],
  "events": [
    {
      "id": "SortButtonClick",
      "event_type": "click",
      "description": "User clicks the sort button to initiate sorting.",
      "trigger_selectors": [
        "#sort-btn"
      ],
      "evidence": [
        "document.getElementById('sort-btn').addEventListener('click', () => {"
      ],
      "confidence": 1
    }
  ],
  "transitions": [
    {
      "from": "S0_Idle",
      "to": "S1_Sorting",
      "event": "SortButtonClick",
      "actions": [],
      "expected_observables": [],
      "evidence": [
        "document.getElementById('sort-btn').addEventListener('click', () => {"
      ],
      "confidence": 1
    },
    {
      "from": "S1_Sorting",
      "to": "S2_Sorted",
      "event": "SortButtonClick",
      "actions": [],
      "expected_observables": [],
      "evidence": [
        "let sortedArr = bubbleSort(arr);"
      ],
      "confidence": 1
    }
  ],
  "components": [
    {
      "type": "input",
      "selector": "#n",
      "text": "",
      "attributes": {
        "type": "number",
        "name": "n"
      },
      "evidence": [
        "<input type=\"number\" id=\"n\" name=\"n\">"
      ]
    },
    {
      "type": "button",
      "selector": "#sort-btn",
      "text": "Sort",
      "attributes": {},
      "evidence": [
        "<button id=\"sort-btn\">Sort</button>"
      ]
    },
    {
      "type": "other",
      "selector": "#result",
      "text": "",
      "attributes": {},
      "evidence": [
        "<p id=\"result\"></p>"
      ]
    }
  ],
  "extraction_summary": {
    "timestamp": "2023-10-03T12:00:00Z",
    "detected_components_count": 3,
    "detected_components": [
      {
        "type": "input",
        "selector": "#n"
      },
      {
        "type": "button",
        "selector": "#sort-btn"
      },
      {
        "type": "other",
        "selector": "#result"
      }
    ],
    "detected_event_handlers_count": 1,
    "detected_event_handlers": [
      "document.getElementById('sort-btn').addEventListener('click', () => {"
    ],
    "extracted_states_count": 3,
    "extracted_transitions_count": 2,
    "extraction_confidence": 1,
    "notes": []
  }
}