{
  "topic": "Interactive Application",
  "description": "Finite state machine for visualizing recursion based on user input.",
  "states": [
    {
      "name": "idle",
      "onEnter": "resetVisualization",
      "onExit": "",
      "on": {
        "VISUALIZE_BUTTON_CLICKED": "visualizing"
      }
    },
    {
      "name": "visualizing",
      "onEnter": "startVisualization",
      "onExit": "clearVisualization",
      "on": {
        "VISUALIZATION_COMPLETE": "done"
      }
    },
    {
      "name": "done",
      "onEnter": "showCompletionFeedback",
      "onExit": "",
      "on": {
        "RESET": "idle"
      }
    }
  ],
  "events": [
    "VISUALIZE_BUTTON_CLICKED",
    "VISUALIZATION_COMPLETE",
    "RESET"
  ],
  "notes": "The 'visualizing' state handles the recursive visualization process, while 'done' indicates the completion of the visualization. The 'idle' state resets the visualization when the user is ready to input a new depth."
}