{
  "topic": "Interactive Application",
  "description": "Finite state machine for an interactive queue management application.",
  "states": [
    {
      "name": "idle",
      "onEnter": "noop",
      "onExit": "noop",
      "on": {
        "ENQUEUE": "updating",
        "DEQUEUE": "updating"
      }
    },
    {
      "name": "updating",
      "onEnter": "updateQueue",
      "onExit": "noop",
      "on": {
        "UPDATE_COMPLETE": "idle"
      }
    }
  ],
  "events": [
    "ENQUEUE",
    "DEQUEUE",
    "UPDATE_COMPLETE"
  ],
  "notes": "The application transitions between idle and updating states based on user interactions with enqueue and dequeue buttons."
}