{
  "meta": {
    "concept": "Binary Search Tree Visualizer",
    "topic": "Data Structures",
    "educational_goal": "To visualize and understand binary search tree operations.",
    "expected_interactions": [
      "Insert a value into the BST",
      "Delete a value from the BST",
      "Search for a value in the BST",
      "Clear the BST",
      "Randomize the BST",
      "Perform in-order traversal",
      "Perform pre-order traversal",
      "Perform post-order traversal",
      "Perform level-order traversal",
      "Step through the traversal",
      "Pause and resume animations"
    ]
  },
  "states": [
    {
      "id": "S0_Idle",
      "label": "Idle",
      "type": "initial",
      "entry_actions": [
        "drawTree()"
      ],
      "exit_actions": [],
      "evidence": [
        "drawTree();"
      ],
      "confidence": 1
    },
    {
      "id": "S1_Inserting",
      "label": "Inserting",
      "type": "action",
      "entry_actions": [
        "animateInsert(value)"
      ],
      "exit_actions": [
        "drawTree({inserted: insertedSet})"
      ],
      "evidence": [
        "document.getElementById('insertBtn').addEventListener('click', ()=>{ const v = parseInt(valueInput.value); animateInsert(v); });"
      ],
      "confidence": 1
    },
    {
      "id": "S2_Deleting",
      "label": "Deleting",
      "type": "action",
      "entry_actions": [
        "animateDelete(value)"
      ],
      "exit_actions": [
        "drawTree({removed: removedSet})"
      ],
      "evidence": [
        "document.getElementById('deleteBtn').addEventListener('click', ()=>{ const v = parseInt(valueInput.value); animateDelete(v); });"
      ],
      "confidence": 1
    },
    {
      "id": "S3_Searching",
      "label": "Searching",
      "type": "action",
      "entry_actions": [
        "animateSearch(value)"
      ],
      "exit_actions": [
        "drawTree({inserted: new Set([res.found.id])})"
      ],
      "evidence": [
        "document.getElementById('searchBtn').addEventListener('click', ()=>{ const v = parseInt(valueInput.value); animateSearch(v); });"
      ],
      "confidence": 1
    },
    {
      "id": "S4_Clearing",
      "label": "Clearing",
      "type": "action",
      "entry_actions": [
        "clearPending(); tree = new BST(); drawTree();"
      ],
      "exit_actions": [],
      "evidence": [
        "document.getElementById('clearBtn').addEventListener('click', ()=>{ clearPending(); tree = new BST(); drawTree(); });"
      ],
      "confidence": 1
    },
    {
      "id": "S5_Randomizing",
      "label": "Randomizing",
      "type": "action",
      "entry_actions": [
        "randomizeTree()"
      ],
      "exit_actions": [
        "drawTree();"
      ],
      "evidence": [
        "document.getElementById('randomBtn').addEventListener('click', ()=>{ randomizeTree(); });"
      ],
      "confidence": 1
    },
    {
      "id": "S6_Traversing",
      "label": "Traversing",
      "type": "action",
      "entry_actions": [
        "animateTraversal(list, name)"
      ],
      "exit_actions": [
        "drawTree();"
      ],
      "evidence": [
        "document.getElementById('inorderBtn').addEventListener('click', ()=>{ const list = tree.inorder(); animateTraversal(list, 'In-order'); });",
        "document.getElementById('preorderBtn').addEventListener('click', ()=>{ const list = tree.preorder(); animateTraversal(list, 'Pre-order'); });",
        "document.getElementById('postorderBtn').addEventListener('click', ()=>{ const list = tree.postorder(); animateTraversal(list, 'Post-order'); });",
        "document.getElementById('levelBtn').addEventListener('click', ()=>{ const list = tree.levelOrder(); animateTraversal(list, 'Level-order'); });"
      ],
      "confidence": 1
    },
    {
      "id": "S7_StepTraversal",
      "label": "Step Traversal",
      "type": "action",
      "entry_actions": [
        "runStepTraversal(list)"
      ],
      "exit_actions": [
        "drawTree();"
      ],
      "evidence": [
        "document.getElementById('stepTraversal').addEventListener('click', ()=>{ runStepTraversal(list); });"
      ],
      "confidence": 1
    },
    {
      "id": "S8_Paused",
      "label": "Paused",
      "type": "action",
      "entry_actions": [
        "paused = true;"
      ],
      "exit_actions": [],
      "evidence": [
        "document.getElementById('pauseBtn').addEventListener('click', ()=>{ paused = true; });"
      ],
      "confidence": 1
    },
    {
      "id": "S9_Resumed",
      "label": "Resumed",
      "type": "action",
      "entry_actions": [
        "paused = false;"
      ],
      "exit_actions": [],
      "evidence": [
        "document.getElementById('resumeBtn').addEventListener('click', ()=>{ paused = false; });"
      ],
      "confidence": 1
    }
  ],
  "events": [
    {
      "id": "INSERT_CLICK",
      "event_type": "click",
      "description": "User clicks the insert button.",
      "trigger_selectors": [
        "#insertBtn"
      ],
      "evidence": [
        "document.getElementById('insertBtn').addEventListener('click', ...);"
      ],
      "confidence": 1
    },
    {
      "id": "DELETE_CLICK",
      "event_type": "click",
      "description": "User clicks the delete button.",
      "trigger_selectors": [
        "#deleteBtn"
      ],
      "evidence": [
        "document.getElementById('deleteBtn').addEventListener('click', ...);"
      ],
      "confidence": 1
    },
    {
      "id": "SEARCH_CLICK",
      "event_type": "click",
      "description": "User clicks the search button.",
      "trigger_selectors": [
        "#searchBtn"
      ],
      "evidence": [
        "document.getElementById('searchBtn').addEventListener('click', ...);"
      ],
      "confidence": 1
    },
    {
      "id": "CLEAR_CLICK",
      "event_type": "click",
      "description": "User clicks the clear button.",
      "trigger_selectors": [
        "#clearBtn"
      ],
      "evidence": [
        "document.getElementById('clearBtn').addEventListener('click', ...);"
      ],
      "confidence": 1
    },
    {
      "id": "RANDOM_CLICK",
      "event_type": "click",
      "description": "User clicks the randomize button.",
      "trigger_selectors": [
        "#randomBtn"
      ],
      "evidence": [
        "document.getElementById('randomBtn').addEventListener('click', ...);"
      ],
      "confidence": 1
    },
    {
      "id": "INORDER_CLICK",
      "event_type": "click",
      "description": "User clicks the in-order traversal button.",
      "trigger_selectors": [
        "#inorderBtn"
      ],
      "evidence": [
        "document.getElementById('inorderBtn').addEventListener('click', ...);"
      ],
      "confidence": 1
    },
    {
      "id": "PREORDER_CLICK",
      "event_type": "click",
      "description": "User clicks the pre-order traversal button.",
      "trigger_selectors": [
        "#preorderBtn"
      ],
      "evidence": [
        "document.getElementById('preorderBtn').addEventListener('click', ...);"
      ],
      "confidence": 1
    },
    {
      "id": "POSTORDER_CLICK",
      "event_type": "click",
      "description": "User clicks the post-order traversal button.",
      "trigger_selectors": [
        "#postorderBtn"
      ],
      "evidence": [
        "document.getElementById('postorderBtn').addEventListener('click', ...);"
      ],
      "confidence": 1
    },
    {
      "id": "LEVEL_CLICK",
      "event_type": "click",
      "description": "User clicks the level-order traversal button.",
      "trigger_selectors": [
        "#levelBtn"
      ],
      "evidence": [
        "document.getElementById('levelBtn').addEventListener('click', ...);"
      ],
      "confidence": 1
    },
    {
      "id": "STEP_CLICK",
      "event_type": "click",
      "description": "User clicks the step traversal button.",
      "trigger_selectors": [
        "#stepTraversal"
      ],
      "evidence": [
        "document.getElementById('stepTraversal').addEventListener('click', ...);"
      ],
      "confidence": 1
    },
    {
      "id": "PAUSE_CLICK",
      "event_type": "click",
      "description": "User clicks the pause button.",
      "trigger_selectors": [
        "#pauseBtn"
      ],
      "evidence": [
        "document.getElementById('pauseBtn').addEventListener('click', ...);"
      ],
      "confidence": 1
    },
    {
      "id": "RESUME_CLICK",
      "event_type": "click",
      "description": "User clicks the resume button.",
      "trigger_selectors": [
        "#resumeBtn"
      ],
      "evidence": [
        "document.getElementById('resumeBtn').addEventListener('click', ...);"
      ],
      "confidence": 1
    }
  ],
  "transitions": [
    {
      "from": "S0_Idle",
      "to": "S1_Inserting",
      "event": "INSERT_CLICK",
      "actions": [],
      "expected_observables": [],
      "evidence": [
        "document.getElementById('insertBtn').addEventListener('click', ...);"
      ],
      "confidence": 1
    },
    {
      "from": "S0_Idle",
      "to": "S2_Deleting",
      "event": "DELETE_CLICK",
      "actions": [],
      "expected_observables": [],
      "evidence": [
        "document.getElementById('deleteBtn').addEventListener('click', ...);"
      ],
      "confidence": 1
    },
    {
      "from": "S0_Idle",
      "to": "S3_Searching",
      "event": "SEARCH_CLICK",
      "actions": [],
      "expected_observables": [],
      "evidence": [
        "document.getElementById('searchBtn').addEventListener('click', ...);"
      ],
      "confidence": 1
    },
    {
      "from": "S0_Idle",
      "to": "S4_Clearing",
      "event": "CLEAR_CLICK",
      "actions": [],
      "expected_observables": [],
      "evidence": [
        "document.getElementById('clearBtn').addEventListener('click', ...);"
      ],
      "confidence": 1
    },
    {
      "from": "S0_Idle",
      "to": "S5_Randomizing",
      "event": "RANDOM_CLICK",
      "actions": [],
      "expected_observables": [],
      "evidence": [
        "document.getElementById('randomBtn').addEventListener('click', ...);"
      ],
      "confidence": 1
    },
    {
      "from": "S0_Idle",
      "to": "S6_Traversing",
      "event": "INORDER_CLICK",
      "actions": [],
      "expected_observables": [],
      "evidence": [
        "document.getElementById('inorderBtn').addEventListener('click', ...);"
      ],
      "confidence": 1
    },
    {
      "from": "S0_Idle",
      "to": "S6_Traversing",
      "event": "PREORDER_CLICK",
      "actions": [],
      "expected_observables": [],
      "evidence": [
        "document.getElementById('preorderBtn').addEventListener('click', ...);"
      ],
      "confidence": 1
    },
    {
      "from": "S0_Idle",
      "to": "S6_Traversing",
      "event": "POSTORDER_CLICK",
      "actions": [],
      "expected_observables": [],
      "evidence": [
        "document.getElementById('postorderBtn').addEventListener('click', ...);"
      ],
      "confidence": 1
    },
    {
      "from": "S0_Idle",
      "to": "S6_Traversing",
      "event": "LEVEL_CLICK",
      "actions": [],
      "expected_observables": [],
      "evidence": [
        "document.getElementById('levelBtn').addEventListener('click', ...);"
      ],
      "confidence": 1
    },
    {
      "from": "S0_Idle",
      "to": "S7_StepTraversal",
      "event": "STEP_CLICK",
      "actions": [],
      "expected_observables": [],
      "evidence": [
        "document.getElementById('stepTraversal').addEventListener('click', ...);"
      ],
      "confidence": 1
    },
    {
      "from": "S0_Idle",
      "to": "S8_Paused",
      "event": "PAUSE_CLICK",
      "actions": [],
      "expected_observables": [],
      "evidence": [
        "document.getElementById('pauseBtn').addEventListener('click', ...);"
      ],
      "confidence": 1
    },
    {
      "from": "S0_Idle",
      "to": "S9_Resumed",
      "event": "RESUME_CLICK",
      "actions": [],
      "expected_observables": [],
      "evidence": [
        "document.getElementById('resumeBtn').addEventListener('click', ...);"
      ],
      "confidence": 1
    }
  ],
  "components": [
    {
      "type": "input",
      "selector": "#valueInput",
      "text": "Value (integer)",
      "attributes": {
        "type": "number",
        "placeholder": "Value (integer)"
      },
      "evidence": [
        "<input id=\"valueInput\" type=\"number\" placeholder=\"Value (integer)\" />"
      ]
    },
    {
      "type": "button",
      "selector": "#insertBtn",
      "text": "Insert",
      "attributes": {
        "class": ""
      },
      "evidence": [
        "<button id=\"insertBtn\">Insert</button>"
      ]
    },
    {
      "type": "button",
      "selector": "#deleteBtn",
      "text": "Delete",
      "attributes": {
        "class": "danger"
      },
      "evidence": [
        "<button id=\"deleteBtn\" class=\"danger\">Delete</button>"
      ]
    },
    {
      "type": "button",
      "selector": "#searchBtn",
      "text": "Search",
      "attributes": {
        "class": "secondary"
      },
      "evidence": [
        "<button id=\"searchBtn\" class=\"secondary\">Search</button>"
      ]
    },
    {
      "type": "button",
      "selector": "#clearBtn",
      "text": "Clear",
      "attributes": {
        "class": "secondary"
      },
      "evidence": [
        "<button id=\"clearBtn\" class=\"secondary\">Clear</button>"
      ]
    },
    {
      "type": "button",
      "selector": "#randomBtn",
      "text": "Randomize",
      "attributes": {
        "class": "secondary"
      },
      "evidence": [
        "<button id=\"randomBtn\" class=\"secondary\">Randomize</button>"
      ]
    },
    {
      "type": "button",
      "selector": "#inorderBtn",
      "text": "In-order",
      "attributes": {
        "class": "secondary"
      },
      "evidence": [
        "<button id=\"inorderBtn\" class=\"secondary\">In-order</button>"
      ]
    },
    {
      "type": "button",
      "selector": "#preorderBtn",
      "text": "Pre-order",
      "attributes": {
        "class": "secondary"
      },
      "evidence": [
        "<button id=\"preorderBtn\" class=\"secondary\">Pre-order</button>"
      ]
    },
    {
      "type": "button",
      "selector": "#postorderBtn",
      "text": "Post-order",
      "attributes": {
        "class": "secondary"
      },
      "evidence": [
        "<button id=\"postorderBtn\" class=\"secondary\">Post-order</button>"
      ]
    },
    {
      "type": "button",
      "selector": "#levelBtn",
      "text": "Level-order",
      "attributes": {
        "class": "secondary"
      },
      "evidence": [
        "<button id=\"levelBtn\" class=\"secondary\">Level-order</button>"
      ]
    },
    {
      "type": "button",
      "selector": "#stepTraversal",
      "text": "Step traversal",
      "attributes": {
        "class": "secondary"
      },
      "evidence": [
        "<button id=\"stepTraversal\" class=\"secondary\">Step traversal</button>"
      ]
    },
    {
      "type": "button",
      "selector": "#pauseBtn",
      "text": "Pause",
      "attributes": {
        "class": "secondary"
      },
      "evidence": [
        "<button id=\"pauseBtn\" class=\"secondary\">Pause</button>"
      ]
    },
    {
      "type": "button",
      "selector": "#resumeBtn",
      "text": "Resume",
      "attributes": {
        "class": "secondary"
      },
      "evidence": [
        "<button id=\"resumeBtn\" class=\"secondary\">Resume</button>"
      ]
    }
  ],
  "extraction_summary": {
    "timestamp": "2023-10-04T12:00:00Z",
    "detected_components_count": 12,
    "detected_components": [
      {
        "type": "input",
        "selector": "#valueInput",
        "text": "Value (integer)",
        "attributes": {
          "type": "number",
          "placeholder": "Value (integer)"
        }
      },
      {
        "type": "button",
        "selector": "#insertBtn",
        "text": "Insert",
        "attributes": {
          "class": ""
        }
      },
      {
        "type": "button",
        "selector": "#deleteBtn",
        "text": "Delete",
        "attributes": {
          "class": "danger"
        }
      },
      {
        "type": "button",
        "selector": "#searchBtn",
        "text": "Search",
        "attributes": {
          "class": "secondary"
        }
      },
      {
        "type": "button",
        "selector": "#clearBtn",
        "text": "Clear",
        "attributes": {
          "class": "secondary"
        }
      },
      {
        "type": "button",
        "selector": "#randomBtn",
        "text": "Randomize",
        "attributes": {
          "class": "secondary"
        }
      },
      {
        "type": "button",
        "selector": "#inorderBtn",
        "text": "In-order",
        "attributes": {
          "class": "secondary"
        }
      },
      {
        "type": "button",
        "selector": "#preorderBtn",
        "text": "Pre-order",
        "attributes": {
          "class": "secondary"
        }
      },
      {
        "type": "button",
        "selector": "#postorderBtn",
        "text": "Post-order",
        "attributes": {
          "class": "secondary"
        }
      },
      {
        "type": "button",
        "selector": "#levelBtn",
        "text": "Level-order",
        "attributes": {
          "class": "secondary"
        }
      },
      {
        "type": "button",
        "selector": "#stepTraversal",
        "text": "Step traversal",
        "attributes": {
          "class": "secondary"
        }
      },
      {
        "type": "button",
        "selector": "#pauseBtn",
        "text": "Pause",
        "attributes": {
          "class": "secondary"
        }
      },
      {
        "type": "button",
        "selector": "#resumeBtn",
        "text": "Resume",
        "attributes": {
          "class": "secondary"
        }
      }
    ],
    "detected_event_handlers_count": 12,
    "detected_event_handlers": [
      "document.getElementById('insertBtn').addEventListener('click', ...);",
      "document.getElementById('deleteBtn').addEventListener('click', ...);",
      "document.getElementById('searchBtn').addEventListener('click', ...);",
      "document.getElementById('clearBtn').addEventListener('click', ...);",
      "document.getElementById('randomBtn').addEventListener('click', ...);",
      "document.getElementById('inorderBtn').addEventListener('click', ...);",
      "document.getElementById('preorderBtn').addEventListener('click', ...);",
      "document.getElementById('postorderBtn').addEventListener('click', ...);",
      "document.getElementById('levelBtn').addEventListener('click', ...);",
      "document.getElementById('stepTraversal').addEventListener('click', ...);",
      "document.getElementById('pauseBtn').addEventListener('click', ...);",
      "document.getElementById('resumeBtn').addEventListener('click', ...);"
    ],
    "extracted_states_count": 10,
    "extracted_transitions_count": 12,
    "extraction_confidence": 1,
    "notes": []
  }
}